spm_kernel/__init__.py
spm_kernel/__main__.py
spm_kernel/kernel.py
spm_kernel/version.py
spm_kernel-1.0.6.dist-info/licenses/LICENSE
spm_kernel-1.0.6.dist-info/METADATA
spm_kernel-1.0.6.dist-info/WHEEL
spm_kernel-1.0.6.dist-info/top_level.txt
spm_kernel-1.0.6.dist-info/RECORD
