Metadata-Version: 2.4
Name: spm_kernel
Version: 1.0.6
Summary: Jupyter kernel for Salford Predictive Modeler (SPM)
Home-page: https://github.com/jlries61/spm_kernel
Author: John L. Ries
Author-email: john@theyarnbard.com
License: GPLv3
License-File: LICENSE
Requires-Dist: IPython
Requires-Dist: metakernel
Requires-Dist: xmltodict
Requires-Dist: numpy
Requires-Dist: pandas
Requires-Dist: matplotlib
Requires-Dist: pexpect
Requires-Dist: ordered-set
Dynamic: author
Dynamic: author-email
Dynamic: description
Dynamic: description-content-type
Dynamic: home-page
Dynamic: license
Dynamic: license-file
Dynamic: requires-dist
Dynamic: summary
